MANIFEST.in
VERSION
setup.py
canonical.ext.google.egg-info/PKG-INFO
canonical.ext.google.egg-info/SOURCES.txt
canonical.ext.google.egg-info/dependency_links.txt
canonical.ext.google.egg-info/entry_points.txt
canonical.ext.google.egg-info/requires.txt
canonical.ext.google.egg-info/top_level.txt
canonical/ext/google/__init__.py
canonical/ext/google/environ.py
canonical/ext/google/package.json
canonical/ext/google/plugin.py
canonical/ext/google/datastore/__init__.py
canonical/ext/google/datastore/_cursor.py
canonical/ext/google/datastore/_datastorerepository.py
canonical/ext/google/datastore/_storage.py
canonical/ext/google/logging/__init__.py
canonical/ext/google/logging/cloudlogginghandler.py
canonical/ext/google/protocols/__init__.py
canonical/ext/google/protocols/idatastorecursor.py
canonical/ext/google/protocols/idatastoreentity.py
canonical/ext/google/protocols/idatastorekey.py
canonical/ext/google/protocols/idatastorequery.py
canonical/ext/google/protocols/idatastoretransaction.py